pyifdm/__init__.py
pyifdm/correlations.py
pyifdm/helpers.py
pyifdm/weights.py
pyifdm/methods/__init__.py
pyifdm/methods/if_aras.py
pyifdm/methods/if_codas.py
pyifdm/methods/if_copras.py
pyifdm/methods/if_edas.py
pyifdm/methods/if_mabac.py
pyifdm/methods/if_mairca.py
pyifdm/methods/if_moora.py
pyifdm/methods/if_topsis.py
pyifdm/methods/if_vikor.py
pyifdm/methods/validator.py
pyifdm/methods/aras/__init__.py
pyifdm/methods/aras/ifs.py
pyifdm/methods/codas/__init__.py
pyifdm/methods/codas/ifs.py
pyifdm/methods/copras/__init__.py
pyifdm/methods/copras/ifs.py
pyifdm/methods/edas/__init__.py
pyifdm/methods/edas/ifs.py
pyifdm/methods/ifs/__init__.py
pyifdm/methods/ifs/distance.py
pyifdm/methods/ifs/normalization.py
pyifdm/methods/ifs/score.py
pyifdm/methods/mabac/__init__.py
pyifdm/methods/mabac/ifs.py
pyifdm/methods/mairca/__init__.py
pyifdm/methods/mairca/ifs.py
pyifdm/methods/moora/__init__.py
pyifdm/methods/moora/ifs.py
pyifdm/methods/topsis/__init__.py
pyifdm/methods/topsis/ifs.py
pyifdm/methods/vikor/__init__.py
pyifdm/methods/vikor/ifs.py
pyifdm-1.0.2.dist-info/LICENSE
pyifdm-1.0.2.dist-info/METADATA
pyifdm-1.0.2.dist-info/WHEEL
pyifdm-1.0.2.dist-info/top_level.txt
pyifdm-1.0.2.dist-info/RECORD
