Metadata-Version: 2.1
Name: pyifdm
Version: 1.0.2
Summary: Python library to support Decision Making with Intuitionistic Fuzzy Sets
Home-page: https://github.com/jwieckowski/pyifdm
Author: Jakub Więckowski
Author-email: J.Wieckowski@il-pib.pl
Classifier: Programming Language :: Python :: 3
Classifier: License :: OSI Approved :: MIT License
Classifier: Operating System :: OS Independent
Requires-Python: >=3.7
License-File: LICENSE
Requires-Dist: numpy
Requires-Dist: scipy
